async_requests/AliveRequests.py
async_requests/__init__.py
async_requests/base.py
async_requests/exceptions.py
async_requests/params.py
async_requests/request.py
async_requests/response.py
async_requests/test.py
async_requests/useragent.py
async_requests/utils.py
await_requests-1.0.3.dist-info/METADATA
await_requests-1.0.3.dist-info/WHEEL
await_requests-1.0.3.dist-info/top_level.txt
await_requests-1.0.3.dist-info/RECORD
