Metadata-Version: 2.1
Name: await-requests
Version: 1.0.3
Summary: UNKNOWN
Home-page: UNKNOWN
License: UNKNOWN
Platform: UNKNOWN
Requires-Dist: PySocks (>=1.7.1)
